cached_httpbl
